{
  "power": {
    "timeUnit": "QUARTER_OF_AN_HOUR",
    "unit": "W",
    "measuredBy": "INVERTER",
    "values": [
      {
        "date": "2022-04-12 00:00:00",
        "value": null
      },
      {
        "date": "2022-04-12 00:15:00",
        "value": null
      },
      {
        "date": "2022-04-12 00:30:00",
        "value": null
      },
      {
        "date": "2022-04-12 00:45:00",
        "value": null
      },
      {
        "date": "2022-04-12 01:00:00",
        "value": null
      },
      {
        "date": "2022-04-12 01:15:00",
        "value": null
      },
      {
        "date": "2022-04-12 01:30:00",
        "value": null
      },
      {
        "date": "2022-04-12 01:45:00",
        "value": null
      },
      {
        "date": "2022-04-12 02:00:00",
        "value": null
      },
      {
        "date": "2022-04-12 02:15:00",
        "value": null
      },
      {
        "date": "2022-04-12 02:30:00",
        "value": null
      },
      {
        "date": "2022-04-12 02:45:00",
        "value": null
      },
      {
        "date": "2022-04-12 03:00:00",
        "value": null
      },
      {
        "date": "2022-04-12 03:15:00",
        "value": null
      },
      {
        "date": "2022-04-12 03:30:00",
        "value": null
      },
      {
        "date": "2022-04-12 03:45:00",
        "value": null
      },
      {
        "date": "2022-04-12 04:00:00",
        "value": null
      },
      {
        "date": "2022-04-12 04:15:00",
        "value": null
      },
      {
        "date": "2022-04-12 04:30:00",
        "value": null
      },
      {
        "date": "2022-04-12 04:45:00",
        "value": null
      },
      {
        "date": "2022-04-12 05:00:00",
        "value": null
      },
      {
        "date": "2022-04-12 05:15:00",
        "value": null
      },
      {
        "date": "2022-04-12 05:30:00",
        "value": null
      },
      {
        "date": "2022-04-12 05:45:00",
        "value": null
      },
      {
        "date": "2022-04-12 06:00:00",
        "value": null
      },
      {
        "date": "2022-04-12 06:15:00",
        "value": null
      },
      {
        "date": "2022-04-12 06:30:00",
        "value": null
      },
      {
        "date": "2022-04-12 06:45:00",
        "value": 0
      },
      {
        "date": "2022-04-12 07:00:00",
        "value": 9.5081625
      },
      {
        "date": "2022-04-12 07:15:00",
        "value": 68.34588
      },
      {
        "date": "2022-04-12 07:30:00",
        "value": 91.269455
      },
      {
        "date": "2022-04-12 07:45:00",
        "value": 147.62497
      },
      {
        "date": "2022-04-12 08:00:00",
        "value": 411.99493
      },
      {
        "date": "2022-04-12 08:15:00",
        "value": 606.5072
      },
      {
        "date": "2022-04-12 08:30:00",
        "value": 910.11646
      },
      {
        "date": "2022-04-12 08:45:00",
        "value": 1109.3408
      },
      {
        "date": "2022-04-12 09:00:00",
        "value": 1046.9282
      },
      {
        "date": "2022-04-12 09:15:00",
        "value": 1530.6919
      },
      {
        "date": "2022-04-12 09:30:00",
        "value": 1776.7855
      },
      {
        "date": "2022-04-12 09:45:00",
        "value": 1957.2863
      },
      {
        "date": "2022-04-12 10:00:00",
        "value": 1892.3052
      },
      {
        "date": "2022-04-12 10:15:00",
        "value": 2196.6013
      },
      {
        "date": "2022-04-12 10:30:00",
        "value": 2421.5798
      },
      {
        "date": "2022-04-12 10:45:00",
        "value": 2439.1433
      },
      {
        "date": "2022-04-12 11:00:00",
        "value": 2716.1362
      },
      {
        "date": "2022-04-12 11:15:00",
        "value": 3004.0007
      },
      {
        "date": "2022-04-12 11:30:00",
        "value": 2638.8635
      },
      {
        "date": "2022-04-12 11:45:00",
        "value": 2839.221
      },
      {
        "date": "2022-04-12 12:00:00",
        "value": 2420.6934
      },
      {
        "date": "2022-04-12 12:15:00",
        "value": 2492.1602
      },
      {
        "date": "2022-04-12 12:30:00",
        "value": 2527.0298
      },
      {
        "date": "2022-04-12 12:45:00",
        "value": 2834.1282
      },
      {
        "date": "2022-04-12 13:00:00",
        "value": 2975.503
      },
      {
        "date": "2022-04-12 13:15:00",
        "value": 2998.4985
      },
      {
        "date": "2022-04-12 13:30:00",
        "value": 3003.3508
      },
      {
        "date": "2022-04-12 13:45:00",
        "value": 2731.3293
      },
      {
        "date": "2022-04-12 14:00:00",
        "value": 2843.1003
      },
      {
        "date": "2022-04-12 14:15:00",
        "value": 2791.4734
      },
      {
        "date": "2022-04-12 14:30:00",
        "value": 2717.9595
      },
      {
        "date": "2022-04-12 14:45:00",
        "value": 3000.8699
      },
      {
        "date": "2022-04-12 15:00:00",
        "value": 2938.0977
      },
      {
        "date": "2022-04-12 15:15:00",
        "value": 2300.2458
      },
      {
        "date": "2022-04-12 15:30:00",
        "value": 2217.021
      },
      {
        "date": "2022-04-12 15:45:00",
        "value": 2000.9308
      },
      {
        "date": "2022-04-12 16:00:00",
        "value": 2030.4631
      },
      {
        "date": "2022-04-12 16:15:00",
        "value": 2128.3853
      },
      {
        "date": "2022-04-12 16:30:00",
        "value": 2647.95
      },
      {
        "date": "2022-04-12 16:45:00",
        "value": 2303.296
      },
      {
        "date": "2022-04-12 17:00:00",
        "value": 1952.6001
      },
      {
        "date": "2022-04-12 17:15:00",
        "value": 1146.8855
      },
      {
        "date": "2022-04-12 17:30:00",
        "value": 937.6252
      },
      {
        "date": "2022-04-12 17:45:00",
        "value": 775.64667
      },
      {
        "date": "2022-04-12 18:00:00",
        "value": 645.5931
      },
      {
        "date": "2022-04-12 18:15:00",
        "value": 600.7677
      },
      {
        "date": "2022-04-12 18:30:00",
        "value": 501.71765
      },
      {
        "date": "2022-04-12 18:45:00",
        "value": 409.3428
      },
      {
        "date": "2022-04-12 19:00:00",
        "value": 331.45813
      },
      {
        "date": "2022-04-12 19:15:00",
        "value": 265.15585
      },
      {
        "date": "2022-04-12 19:30:00",
        "value": 164.79459
      },
      {
        "date": "2022-04-12 19:45:00",
        "value": 48.68997
      },
      {
        "date": "2022-04-12 20:00:00",
        "value": 6.0474873
      },
      {
        "date": "2022-04-12 20:15:00",
        "value": 0
      },
      {
        "date": "2022-04-12 20:30:00",
        "value": null
      },
      {
        "date": "2022-04-12 20:45:00",
        "value": null
      },
      {
        "date": "2022-04-12 21:00:00",
        "value": null
      },
      {
        "date": "2022-04-12 21:15:00",
        "value": null
      },
      {
        "date": "2022-04-12 21:30:00",
        "value": null
      },
      {
        "date": "2022-04-12 21:45:00",
        "value": null
      },
      {
        "date": "2022-04-12 22:00:00",
        "value": null
      },
      {
        "date": "2022-04-12 22:15:00",
        "value": null
      },
      {
        "date": "2022-04-12 22:30:00",
        "value": null
      },
      {
        "date": "2022-04-12 22:45:00",
        "value": null
      },
      {
        "date": "2022-04-12 23:00:00",
        "value": null
      },
      {
        "date": "2022-04-12 23:15:00",
        "value": null
      },
      {
        "date": "2022-04-12 23:30:00",
        "value": null
      },
      {
        "date": "2022-04-12 23:45:00",
        "value": null
      }
    ]
  }
}
