{
  "power": {
    "timeUnit": "QUARTER_OF_AN_HOUR",
    "unit": "W",
    "measuredBy": "INVERTER",
    "values": [
      {
        "date": "2023-02-06 00:00:00",
        "value": null
      },
      {
        "date": "2023-02-06 00:15:00",
        "value": null
      },
      {
        "date": "2023-02-06 00:30:00",
        "value": null
      },
      {
        "date": "2023-02-06 00:45:00",
        "value": null
      },
      {
        "date": "2023-02-06 01:00:00",
        "value": null
      },
      {
        "date": "2023-02-06 01:15:00",
        "value": null
      },
      {
        "date": "2023-02-06 01:30:00",
        "value": null
      },
      {
        "date": "2023-02-06 01:45:00",
        "value": null
      },
      {
        "date": "2023-02-06 02:00:00",
        "value": null
      },
      {
        "date": "2023-02-06 02:15:00",
        "value": null
      },
      {
        "date": "2023-02-06 02:30:00",
        "value": null
      },
      {
        "date": "2023-02-06 02:45:00",
        "value": null
      },
      {
        "date": "2023-02-06 03:00:00",
        "value": null
      },
      {
        "date": "2023-02-06 03:15:00",
        "value": null
      },
      {
        "date": "2023-02-06 03:30:00",
        "value": null
      },
      {
        "date": "2023-02-06 03:45:00",
        "value": null
      },
      {
        "date": "2023-02-06 04:00:00",
        "value": null
      },
      {
        "date": "2023-02-06 04:15:00",
        "value": null
      },
      {
        "date": "2023-02-06 04:30:00",
        "value": null
      },
      {
        "date": "2023-02-06 04:45:00",
        "value": null
      },
      {
        "date": "2023-02-06 05:00:00",
        "value": null
      },
      {
        "date": "2023-02-06 05:15:00",
        "value": null
      },
      {
        "date": "2023-02-06 05:30:00",
        "value": 0
      },
      {
        "date": "2023-02-06 05:45:00",
        "value": null
      },
      {
        "date": "2023-02-06 06:00:00",
        "value": null
      },
      {
        "date": "2023-02-06 06:15:00",
        "value": null
      },
      {
        "date": "2023-02-06 06:30:00",
        "value": null
      },
      {
        "date": "2023-02-06 06:45:00",
        "value": null
      },
      {
        "date": "2023-02-06 07:00:00",
        "value": null
      },
      {
        "date": "2023-02-06 07:15:00",
        "value": null
      },
      {
        "date": "2023-02-06 07:30:00",
        "value": null
      },
      {
        "date": "2023-02-06 07:45:00",
        "value": null
      },
      {
        "date": "2023-02-06 08:00:00",
        "value": null
      },
      {
        "date": "2023-02-06 08:15:00",
        "value": 0
      },
      {
        "date": "2023-02-06 08:30:00",
        "value": 6.5339375
      },
      {
        "date": "2023-02-06 08:45:00",
        "value": 10.598868
      },
      {
        "date": "2023-02-06 09:00:00",
        "value": 71.34055
      },
      {
        "date": "2023-02-06 09:15:00",
        "value": 148.23073
      },
      {
        "date": "2023-02-06 09:30:00",
        "value": 315.338
      },
      {
        "date": "2023-02-06 09:45:00",
        "value": 459.9285
      },
      {
        "date": "2023-02-06 10:00:00",
        "value": 437.4816
      },
      {
        "date": "2023-02-06 10:15:00",
        "value": 459.17856
      },
      {
        "date": "2023-02-06 10:30:00",
        "value": 571.5795
      },
      {
        "date": "2023-02-06 10:45:00",
        "value": 604.7161
      },
      {
        "date": "2023-02-06 11:00:00",
        "value": 578.66644
      },
      {
        "date": "2023-02-06 11:15:00",
        "value": 626.6362
      },
      {
        "date": "2023-02-06 11:30:00",
        "value": 570.1823
      },
      {
        "date": "2023-02-06 11:45:00",
        "value": 811.20215
      },
      {
        "date": "2023-02-06 12:00:00",
        "value": 1047.1891
      },
      {
        "date": "2023-02-06 12:15:00",
        "value": 725.68713
      },
      {
        "date": "2023-02-06 12:30:00",
        "value": 736.58527
      },
      {
        "date": "2023-02-06 12:45:00",
        "value": 757.5553
      },
      {
        "date": "2023-02-06 13:00:00",
        "value": 1024.3534
      },
      {
        "date": "2023-02-06 13:15:00",
        "value": 666.5205
      },
      {
        "date": "2023-02-06 13:30:00",
        "value": 557.0499
      },
      {
        "date": "2023-02-06 13:45:00",
        "value": null
      },
      {
        "date": "2023-02-06 14:00:00",
        "value": null
      },
      {
        "date": "2023-02-06 14:15:00",
        "value": null
      },
      {
        "date": "2023-02-06 14:30:00",
        "value": null
      },
      {
        "date": "2023-02-06 14:45:00",
        "value": null
      },
      {
        "date": "2023-02-06 15:00:00",
        "value": null
      },
      {
        "date": "2023-02-06 15:15:00",
        "value": null
      },
      {
        "date": "2023-02-06 15:30:00",
        "value": null
      },
      {
        "date": "2023-02-06 15:45:00",
        "value": null
      },
      {
        "date": "2023-02-06 16:00:00",
        "value": null
      },
      {
        "date": "2023-02-06 16:15:00",
        "value": null
      },
      {
        "date": "2023-02-06 16:30:00",
        "value": null
      },
      {
        "date": "2023-02-06 16:45:00",
        "value": null
      },
      {
        "date": "2023-02-06 17:00:00",
        "value": null
      },
      {
        "date": "2023-02-06 17:15:00",
        "value": null
      },
      {
        "date": "2023-02-06 17:30:00",
        "value": null
      },
      {
        "date": "2023-02-06 17:45:00",
        "value": null
      },
      {
        "date": "2023-02-06 18:00:00",
        "value": null
      },
      {
        "date": "2023-02-06 18:15:00",
        "value": null
      },
      {
        "date": "2023-02-06 18:30:00",
        "value": null
      },
      {
        "date": "2023-02-06 18:45:00",
        "value": null
      },
      {
        "date": "2023-02-06 19:00:00",
        "value": null
      },
      {
        "date": "2023-02-06 19:15:00",
        "value": null
      },
      {
        "date": "2023-02-06 19:30:00",
        "value": null
      },
      {
        "date": "2023-02-06 19:45:00",
        "value": null
      },
      {
        "date": "2023-02-06 20:00:00",
        "value": null
      },
      {
        "date": "2023-02-06 20:15:00",
        "value": null
      },
      {
        "date": "2023-02-06 20:30:00",
        "value": null
      },
      {
        "date": "2023-02-06 20:45:00",
        "value": null
      },
      {
        "date": "2023-02-06 21:00:00",
        "value": null
      },
      {
        "date": "2023-02-06 21:15:00",
        "value": null
      },
      {
        "date": "2023-02-06 21:30:00",
        "value": null
      },
      {
        "date": "2023-02-06 21:45:00",
        "value": null
      },
      {
        "date": "2023-02-06 22:00:00",
        "value": null
      },
      {
        "date": "2023-02-06 22:15:00",
        "value": null
      },
      {
        "date": "2023-02-06 22:30:00",
        "value": null
      },
      {
        "date": "2023-02-06 22:45:00",
        "value": null
      },
      {
        "date": "2023-02-06 23:00:00",
        "value": null
      },
      {
        "date": "2023-02-06 23:15:00",
        "value": null
      },
      {
        "date": "2023-02-06 23:30:00",
        "value": null
      },
      {
        "date": "2023-02-06 23:45:00",
        "value": null
      }
    ]
  }
}
