{
  "power": {
    "timeUnit": "QUARTER_OF_AN_HOUR",
    "unit": "W",
    "measuredBy": "INVERTER",
    "values": [
      {
        "date": "2023-07-09 00:00:00",
        "value": null
      },
      {
        "date": "2023-07-09 00:15:00",
        "value": null
      },
      {
        "date": "2023-07-09 00:30:00",
        "value": null
      },
      {
        "date": "2023-07-09 00:45:00",
        "value": null
      },
      {
        "date": "2023-07-09 01:00:00",
        "value": null
      },
      {
        "date": "2023-07-09 01:15:00",
        "value": null
      },
      {
        "date": "2023-07-09 01:30:00",
        "value": null
      },
      {
        "date": "2023-07-09 01:45:00",
        "value": null
      },
      {
        "date": "2023-07-09 02:00:00",
        "value": null
      },
      {
        "date": "2023-07-09 02:15:00",
        "value": null
      },
      {
        "date": "2023-07-09 02:30:00",
        "value": null
      },
      {
        "date": "2023-07-09 02:45:00",
        "value": null
      },
      {
        "date": "2023-07-09 03:00:00",
        "value": null
      },
      {
        "date": "2023-07-09 03:15:00",
        "value": null
      },
      {
        "date": "2023-07-09 03:30:00",
        "value": null
      },
      {
        "date": "2023-07-09 03:45:00",
        "value": null
      },
      {
        "date": "2023-07-09 04:00:00",
        "value": null
      },
      {
        "date": "2023-07-09 04:15:00",
        "value": null
      },
      {
        "date": "2023-07-09 04:30:00",
        "value": null
      },
      {
        "date": "2023-07-09 04:45:00",
        "value": null
      },
      {
        "date": "2023-07-09 05:00:00",
        "value": null
      },
      {
        "date": "2023-07-09 05:15:00",
        "value": null
      },
      {
        "date": "2023-07-09 05:30:00",
        "value": 0
      },
      {
        "date": "2023-07-09 05:45:00",
        "value": 3.4563715
      },
      {
        "date": "2023-07-09 06:00:00",
        "value": 39.161766
      },
      {
        "date": "2023-07-09 06:15:00",
        "value": 82.65506
      },
      {
        "date": "2023-07-09 06:30:00",
        "value": 131.02675
      },
      {
        "date": "2023-07-09 06:45:00",
        "value": 179.17586
      },
      {
        "date": "2023-07-09 07:00:00",
        "value": 243.44722
      },
      {
        "date": "2023-07-09 07:15:00",
        "value": 340.83795
      },
      {
        "date": "2023-07-09 07:30:00",
        "value": 482.1268
      },
      {
        "date": "2023-07-09 07:45:00",
        "value": 637.1788
      },
      {
        "date": "2023-07-09 08:00:00",
        "value": 813.81537
      },
      {
        "date": "2023-07-09 08:15:00",
        "value": 942.00525
      },
      {
        "date": "2023-07-09 08:30:00",
        "value": 1131.401
      },
      {
        "date": "2023-07-09 08:45:00",
        "value": 1305.2979
      },
      {
        "date": "2023-07-09 09:00:00",
        "value": 1490.6066
      },
      {
        "date": "2023-07-09 09:15:00",
        "value": 1692.8088
      },
      {
        "date": "2023-07-09 09:30:00",
        "value": 1901.1396
      },
      {
        "date": "2023-07-09 09:45:00",
        "value": 2031.0505
      },
      {
        "date": "2023-07-09 10:00:00",
        "value": 2192.9602
      },
      {
        "date": "2023-07-09 10:15:00",
        "value": 2342.5967
      },
      {
        "date": "2023-07-09 10:30:00",
        "value": 2512.1912
      },
      {
        "date": "2023-07-09 10:45:00",
        "value": 2666.647
      },
      {
        "date": "2023-07-09 11:00:00",
        "value": 2792.4941
      },
      {
        "date": "2023-07-09 11:15:00",
        "value": 2888.984
      },
      {
        "date": "2023-07-09 11:30:00",
        "value": 2968.8499
      },
      {
        "date": "2023-07-09 11:45:00",
        "value": 3004.9656
      },
      {
        "date": "2023-07-09 12:00:00",
        "value": 3003.2454
      },
      {
        "date": "2023-07-09 12:15:00",
        "value": 2999.5166
      },
      {
        "date": "2023-07-09 12:30:00",
        "value": 2346.845
      },
      {
        "date": "2023-07-09 12:45:00",
        "value": 1937.4988
      },
      {
        "date": "2023-07-09 13:00:00",
        "value": 1162.2389
      },
      {
        "date": "2023-07-09 13:15:00",
        "value": 969.208
      },
      {
        "date": "2023-07-09 13:30:00",
        "value": 838.1557
      },
      {
        "date": "2023-07-09 13:45:00",
        "value": 364.45148
      },
      {
        "date": "2023-07-09 14:00:00",
        "value": 171.39352
      },
      {
        "date": "2023-07-09 14:15:00",
        "value": 70.434685
      },
      {
        "date": "2023-07-09 14:30:00",
        "value": 45.892967
      },
      {
        "date": "2023-07-09 14:45:00",
        "value": null
      },
      {
        "date": "2023-07-09 15:00:00",
        "value": null
      },
      {
        "date": "2023-07-09 15:15:00",
        "value": null
      },
      {
        "date": "2023-07-09 15:30:00",
        "value": null
      },
      {
        "date": "2023-07-09 15:45:00",
        "value": null
      },
      {
        "date": "2023-07-09 16:00:00",
        "value": null
      },
      {
        "date": "2023-07-09 16:15:00",
        "value": null
      },
      {
        "date": "2023-07-09 16:30:00",
        "value": null
      },
      {
        "date": "2023-07-09 16:45:00",
        "value": null
      },
      {
        "date": "2023-07-09 17:00:00",
        "value": null
      },
      {
        "date": "2023-07-09 17:15:00",
        "value": null
      },
      {
        "date": "2023-07-09 17:30:00",
        "value": null
      },
      {
        "date": "2023-07-09 17:45:00",
        "value": null
      },
      {
        "date": "2023-07-09 18:00:00",
        "value": null
      },
      {
        "date": "2023-07-09 18:15:00",
        "value": null
      },
      {
        "date": "2023-07-09 18:30:00",
        "value": null
      },
      {
        "date": "2023-07-09 18:45:00",
        "value": null
      },
      {
        "date": "2023-07-09 19:00:00",
        "value": null
      },
      {
        "date": "2023-07-09 19:15:00",
        "value": null
      },
      {
        "date": "2023-07-09 19:30:00",
        "value": null
      },
      {
        "date": "2023-07-09 19:45:00",
        "value": null
      },
      {
        "date": "2023-07-09 20:00:00",
        "value": null
      },
      {
        "date": "2023-07-09 20:15:00",
        "value": null
      },
      {
        "date": "2023-07-09 20:30:00",
        "value": null
      },
      {
        "date": "2023-07-09 20:45:00",
        "value": null
      },
      {
        "date": "2023-07-09 21:00:00",
        "value": null
      },
      {
        "date": "2023-07-09 21:15:00",
        "value": null
      },
      {
        "date": "2023-07-09 21:30:00",
        "value": null
      },
      {
        "date": "2023-07-09 21:45:00",
        "value": null
      },
      {
        "date": "2023-07-09 22:00:00",
        "value": null
      },
      {
        "date": "2023-07-09 22:15:00",
        "value": null
      },
      {
        "date": "2023-07-09 22:30:00",
        "value": null
      },
      {
        "date": "2023-07-09 22:45:00",
        "value": null
      },
      {
        "date": "2023-07-09 23:00:00",
        "value": null
      },
      {
        "date": "2023-07-09 23:15:00",
        "value": null
      },
      {
        "date": "2023-07-09 23:30:00",
        "value": null
      },
      {
        "date": "2023-07-09 23:45:00",
        "value": null
      }
    ]
  }
}
