{
  "power": {
    "timeUnit": "QUARTER_OF_AN_HOUR",
    "unit": "W",
    "measuredBy": "INVERTER",
    "values": [
      {
        "date": "2020-06-01 00:00:00",
        "value": null
      },
      {
        "date": "2020-06-01 00:15:00",
        "value": null
      },
      {
        "date": "2020-06-01 00:30:00",
        "value": null
      },
      {
        "date": "2020-06-01 00:45:00",
        "value": null
      },
      {
        "date": "2020-06-01 01:00:00",
        "value": 0
      },
      {
        "date": "2020-06-01 01:15:00",
        "value": null
      },
      {
        "date": "2020-06-01 01:30:00",
        "value": null
      },
      {
        "date": "2020-06-01 01:45:00",
        "value": null
      },
      {
        "date": "2020-06-01 02:00:00",
        "value": null
      },
      {
        "date": "2020-06-01 02:15:00",
        "value": null
      },
      {
        "date": "2020-06-01 02:30:00",
        "value": null
      },
      {
        "date": "2020-06-01 02:45:00",
        "value": null
      },
      {
        "date": "2020-06-01 03:00:00",
        "value": null
      },
      {
        "date": "2020-06-01 03:15:00",
        "value": null
      },
      {
        "date": "2020-06-01 03:30:00",
        "value": null
      },
      {
        "date": "2020-06-01 03:45:00",
        "value": null
      },
      {
        "date": "2020-06-01 04:00:00",
        "value": null
      },
      {
        "date": "2020-06-01 04:15:00",
        "value": null
      },
      {
        "date": "2020-06-01 04:30:00",
        "value": null
      },
      {
        "date": "2020-06-01 04:45:00",
        "value": null
      },
      {
        "date": "2020-06-01 05:00:00",
        "value": null
      },
      {
        "date": "2020-06-01 05:15:00",
        "value": null
      },
      {
        "date": "2020-06-01 05:30:00",
        "value": 0
      },
      {
        "date": "2020-06-01 05:45:00",
        "value": 16.893867
      },
      {
        "date": "2020-06-01 06:00:00",
        "value": 49.46595
      },
      {
        "date": "2020-06-01 06:15:00",
        "value": 81.89536
      },
      {
        "date": "2020-06-01 06:30:00",
        "value": 121.74868
      },
      {
        "date": "2020-06-01 06:45:00",
        "value": 177.85876
      },
      {
        "date": "2020-06-01 07:00:00",
        "value": 275.24997
      },
      {
        "date": "2020-06-01 07:15:00",
        "value": 415.42563
      },
      {
        "date": "2020-06-01 07:30:00",
        "value": 667.8684
      },
      {
        "date": "2020-06-01 07:45:00",
        "value": 988.0659
      },
      {
        "date": "2020-06-01 08:00:00",
        "value": 1224.7451
      },
      {
        "date": "2020-06-01 08:15:00",
        "value": 1318.6484
      },
      {
        "date": "2020-06-01 08:30:00",
        "value": 1592.3135
      },
      {
        "date": "2020-06-01 08:45:00",
        "value": 1832.0426
      },
      {
        "date": "2020-06-01 09:00:00",
        "value": 1872.274
      },
      {
        "date": "2020-06-01 09:15:00",
        "value": 2162.5483
      },
      {
        "date": "2020-06-01 09:30:00",
        "value": 2383.5918
      },
      {
        "date": "2020-06-01 09:45:00",
        "value": 2570.7432
      },
      {
        "date": "2020-06-01 10:00:00",
        "value": 2747.0115
      },
      {
        "date": "2020-06-01 10:15:00",
        "value": 2916.666
      },
      {
        "date": "2020-06-01 10:30:00",
        "value": 2999.0332
      },
      {
        "date": "2020-06-01 10:45:00",
        "value": 2999.3557
      },
      {
        "date": "2020-06-01 11:00:00",
        "value": 3002.0286
      },
      {
        "date": "2020-06-01 11:15:00",
        "value": 2995.5547
      },
      {
        "date": "2020-06-01 11:30:00",
        "value": 2995.0073
      },
      {
        "date": "2020-06-01 11:45:00",
        "value": 2995.8152
      },
      {
        "date": "2020-06-01 12:00:00",
        "value": 2994.8108
      },
      {
        "date": "2020-06-01 12:15:00",
        "value": 2988.6418
      },
      {
        "date": "2020-06-01 12:30:00",
        "value": 2987.6658
      },
      {
        "date": "2020-06-01 12:45:00",
        "value": 2992.359
      },
      {
        "date": "2020-06-01 13:00:00",
        "value": 2991.351
      },
      {
        "date": "2020-06-01 13:15:00",
        "value": 2998.08
      },
      {
        "date": "2020-06-01 13:30:00",
        "value": 2996.7263
      },
      {
        "date": "2020-06-01 13:45:00",
        "value": 2997.3508
      },
      {
        "date": "2020-06-01 14:00:00",
        "value": 2999.2893
      },
      {
        "date": "2020-06-01 14:15:00",
        "value": 2990.8281
      },
      {
        "date": "2020-06-01 14:30:00",
        "value": 2990.0476
      },
      {
        "date": "2020-06-01 14:45:00",
        "value": 2991.2205
      },
      {
        "date": "2020-06-01 15:00:00",
        "value": 3000.1936
      },
      {
        "date": "2020-06-01 15:15:00",
        "value": 2995.8103
      },
      {
        "date": "2020-06-01 15:30:00",
        "value": 2996.583
      },
      {
        "date": "2020-06-01 15:45:00",
        "value": 2996.7349
      },
      {
        "date": "2020-06-01 16:00:00",
        "value": 2994.6418
      },
      {
        "date": "2020-06-01 16:15:00",
        "value": 2969.8303
      },
      {
        "date": "2020-06-01 16:30:00",
        "value": 2314.6304
      },
      {
        "date": "2020-06-01 16:45:00",
        "value": 2876.8115
      },
      {
        "date": "2020-06-01 17:00:00",
        "value": 2936.0486
      },
      {
        "date": "2020-06-01 17:15:00",
        "value": 2198.3271
      },
      {
        "date": "2020-06-01 17:30:00",
        "value": 1923.342
      },
      {
        "date": "2020-06-01 17:45:00",
        "value": 1698.0631
      },
      {
        "date": "2020-06-01 18:00:00",
        "value": 2035.5818
      },
      {
        "date": "2020-06-01 18:15:00",
        "value": 1724.6786
      },
      {
        "date": "2020-06-01 18:30:00",
        "value": 1842.2954
      },
      {
        "date": "2020-06-01 18:45:00",
        "value": 1700.1816
      },
      {
        "date": "2020-06-01 19:00:00",
        "value": 800.6055
      },
      {
        "date": "2020-06-01 19:15:00",
        "value": 672.9767
      },
      {
        "date": "2020-06-01 19:30:00",
        "value": 765.9157
      },
      {
        "date": "2020-06-01 19:45:00",
        "value": 612.6378
      },
      {
        "date": "2020-06-01 20:00:00",
        "value": 275.1388
      },
      {
        "date": "2020-06-01 20:15:00",
        "value": 297.58755
      },
      {
        "date": "2020-06-01 20:30:00",
        "value": 183.98355
      },
      {
        "date": "2020-06-01 20:45:00",
        "value": 109.361565
      },
      {
        "date": "2020-06-01 21:00:00",
        "value": 70.871216
      },
      {
        "date": "2020-06-01 21:15:00",
        "value": 31.488503
      },
      {
        "date": "2020-06-01 21:30:00",
        "value": 0
      },
      {
        "date": "2020-06-01 21:45:00",
        "value": 0
      },
      {
        "date": "2020-06-01 22:00:00",
        "value": null
      },
      {
        "date": "2020-06-01 22:15:00",
        "value": null
      },
      {
        "date": "2020-06-01 22:30:00",
        "value": null
      },
      {
        "date": "2020-06-01 22:45:00",
        "value": null
      },
      {
        "date": "2020-06-01 23:00:00",
        "value": null
      },
      {
        "date": "2020-06-01 23:15:00",
        "value": null
      },
      {
        "date": "2020-06-01 23:30:00",
        "value": null
      },
      {
        "date": "2020-06-01 23:45:00",
        "value": null
      }
    ]
  }
}
